bpmn_print/__init__.py
bpmn_print/bpmn_data.py
bpmn_print/bpmn_diagram.py
bpmn_print/cli.py
bpmn_print/console.py
bpmn_print/diagram_model.py
bpmn_print/errors.py
bpmn_print/node_styles.py
bpmn_print/path_utils.py
bpmn_print/pdf.py
bpmn_print/pretty_print.py
bpmn_print/xml_constants.py
bpmn_print/xml_utils.py
bpmn_print-0.4.1.dist-info/METADATA
bpmn_print-0.4.1.dist-info/WHEEL
bpmn_print-0.4.1.dist-info/entry_points.txt
bpmn_print-0.4.1.dist-info/licenses/LICENSE
bpmn_print-0.4.1.dist-info/RECORD
