Metadata-Version: 2.4
Name: bpmn_print
Version: 0.4.1
Summary: Print BPMN workflow for developer readings
License: MIT
License-File: LICENSE
Keywords: kafka
Author: Siak Hooi
Author-email: siakhooi@gmail.com
Requires-Python: >=3.10,<4.0
Classifier: Development Status :: 4 - Beta
Classifier: Environment :: Console
Classifier: License :: OSI Approved :: MIT License
Classifier: Topic :: Utilities
Requires-Dist: graphviz (>=0.21,<0.22)
Requires-Dist: lxml (>=6.0.2,<7.0.0)
Requires-Dist: pillow (>=11.0.0,<12.0.0)
Requires-Dist: reportlab (>=4.4.5,<5.0.0)
Project-URL: Bug Tracker, https://github.com/siakhooi/bpmn-print/issues
Project-URL: Documentation, https://github.com/siakhooi/bpmn-print/wiki
Project-URL: Homepage, https://github.com/siakhooi/bpmn-print
Project-URL: Repository, https://github.com/siakhooi/bpmn-print
